hubitatcontrol/__init__.py
hubitatcontrol/__main__.py
hubitatcontrol/environment.py
hubitatcontrol/generic.py
hubitatcontrol/hub.py
hubitatcontrol/lights.py
hubitatcontrol/sensors.py
hubitatcontrol-3.0.2.dist-info/METADATA
hubitatcontrol-3.0.2.dist-info/WHEEL
hubitatcontrol-3.0.2.dist-info/entry_points.txt
hubitatcontrol-3.0.2.dist-info/RECORD
