Metadata-Version: 2.1
Name: hubitatcontrol
Version: 3.0.2
Summary: Hubitat Maker API Interface
Home-page: https://pypi.org/project/hubitatcontrol
License: MIT
Keywords: hubitat,makerapi,requests
Author: Jelloeater
Author-email: jello@jelloeater.me
Requires-Python: >=3.10,<4.0
Classifier: Development Status :: 5 - Production/Stable
Classifier: Environment :: No Input/Output (Daemon)
Classifier: Intended Audience :: Developers
Classifier: License :: OSI Approved :: MIT License
Classifier: Operating System :: OS Independent
Classifier: Programming Language :: Python :: 3
Classifier: Programming Language :: Python :: 3.10
Classifier: Programming Language :: Python :: 3.11
Classifier: Programming Language :: Python :: 3.12
Classifier: Programming Language :: Python :: 3.13
Classifier: Topic :: Home Automation
Requires-Dist: keyring (>=23.13.1,<24.0.0)
Requires-Dist: prettytable
Requires-Dist: requests (==2.32.3)
Requires-Dist: typer
Project-URL: Documentation, https://github.com/Jelloeater/hubitatcontrol/tree/main/docs
Project-URL: Repository, https://github.com/Jelloeater/hubitatcontrol
